CHANGES.txt
LICENSE
MANIFEST.in
README.rst
setup.py
foreman/__init__.py
foreman/api.py
foreman/architectures.py
foreman/computeResources.py
foreman/configTemplates.py
foreman/environments.py
foreman/freeip.py
foreman/hostgroups.py
foreman/hosts.py
foreman/item.py
foreman/itemComputeRessource.py
foreman/itemConfigTemplate.py
foreman/itemHost.py
foreman/itemHostsGroup.py
foreman/itemOperatingSystem.py
foreman/itemPuppetClass.py
foreman/itemSmartClassParameter.py
foreman/objects.py
foreman/operatingsystems.py
foreman/puppetClasses.py
foreman/smartClassParameters.py
foreman/smartProxies.py
foreman/subDict.py
foreman/subItem.py
foreman/subItemArchitecture.py
foreman/subItemConfigTemplate.py
foreman/subItemImages.py
foreman/subItemInterface.py
foreman/subItemMedia.py
foreman/subItemOperatingSystem.py
foreman/subItemOsDefaultTemplate.py
foreman/subItemOverrideValues.py
foreman/subItemPTable.py
foreman/subItemParameter.py
foreman/subItemPuppetClassIds.py
foreman/subItemPuppetClasses.py
foreman/subItemSmartClassParameter.py
foreman/subnets.py
foreman.egg-info/PKG-INFO
foreman.egg-info/SOURCES.txt
foreman.egg-info/dependency_links.txt
foreman.egg-info/requires.txt
foreman.egg-info/top_level.txt