Metadata-Version: 1.1
Name: foreman
Version: 0.9.4
Summary: Python library to manipulate The Foreman through the API
Home-page: https://github.com/davidblaisonneau-orange/foreman
Author: David Blaisonneau, Arnaud Morin
Author-email: david.blaisonneau@orange.com, arnaud1.morin@orange.com
License:                                  Apache License
